wp2hugo/__init__.py
wp2hugo/__main__.py
wp2hugo/commands.py
wp2hugo/lang_detection.py
wp2hugo-0.1.5.dist-info/LICENSE
wp2hugo-0.1.5.dist-info/METADATA
wp2hugo-0.1.5.dist-info/WHEEL
wp2hugo-0.1.5.dist-info/entry_points.txt
wp2hugo-0.1.5.dist-info/top_level.txt
wp2hugo-0.1.5.dist-info/RECORD
