Metadata-Version: 2.1
Name: wp2hugo
Version: 0.1.5
Summary: A Python CLI application that converts a WordPress WXR backup file to MD files usable by Hugo.
Author-email: Jostein Elvaker Haande <tolecnal@tolecnal.net>
Project-URL: homepage, https://tolecnal.net
Project-URL: repository, https://github.com/tolecnal/wp2hugo
Project-URL: changelog, https://github.com/tolecnal/wp2hugo/blob/main/CHANGELOG.md
Project-URL: documentation, https://github.com/tolecnal/wp2hugo/blob/main/README.md
Project-URL: bugs, https://github.com/tolecnal/wp2hugo/issues
Project-URL: issues, https://github.com/tolecnal/wp2hugo/issues
Project-URL: tracker, https://github.com/tolecnal/wp2hugo/issues
Classifier: Development Status :: 4 - Beta
Classifier: Environment :: Console
Classifier: Intended Audience :: Developers
Classifier: License :: OSI Approved :: MIT License
Classifier: Operating System :: MacOS
Classifier: Operating System :: Microsoft :: Windows
Classifier: Operating System :: Unix
Classifier: Topic :: Internet :: WWW/HTTP
Requires-Python: >3.8
License-File: LICENSE
Requires-Dist: click >=8.1.7
Requires-Dist: PyYAML >=6.0.1
Requires-Dist: markdownify >=0.11.6
Requires-Dist: markdown-it-py >=3.0.0
Requires-Dist: magika >=0.5.0
